{"Player": {"0": "deandre jordan", "1": "deandre jordan", "2": "deandre jordan", "3": "deandre jordan", "4": "deandre jordan", "5": "deandre jordan", "6": "deandre jordan", "7": "deandre jordan", "8": "deandre jordan", "9": "deandre jordan", "10": "deandre jordan", "11": "deandre jordan", "12": "deandre jordan"}, "Season": {"0": "2023-24", "1": "2023-24", "2": "2023-24", "3": "2023-24", "4": "2023-24", "5": "2023-24", "6": "2023-24", "7": "2023-24", "8": "2023-24", "9": "2023-24", "10": "2023-24", "11": "2023-24", "12": "2023-24"}, "Type": {"0": "Regular", "1": "Regular", "2": "Regular", "3": "Regular", "4": "Regular", "5": "Regular", "6": "Regular", "7": "Regular", "8": "Regular", "9": "Regular", "10": "Preseason", "11": "Preseason", "12": "Preseason"}, "Date": {"0": "Thu 12/14", "1": "Tue 12/12", "2": "Fri 12/8", "3": "Wed 12/6", "4": "Sat 12/2", "5": "Fri 12/1", "6": "Wed 11/29", "7": "Mon 11/27", "8": "Sun 11/26", "9": "Sat 11/4", "10": "Tue 10/17", "11": "Thu 10/12", "12": "Tue 10/10"}, "OPP": {"0": "vsBKN", "1": "@CHI", "2": "vsHOU", "3": "@LAC", "4": "@SAC", "5": "@PHX", "6": "vsHOU", "7": "@LAC", "8": "vsSA", "9": "vsCHI", "10": "@LAC", "11": "@CHI", "12": "@PHX"}, "Result": {"0": "W124-101", "1": "W114-106", "2": "L114-106", "3": "L111-102", "4": "L123-117", "5": "W119-111", "6": "W134-124", "7": "W113-104", "8": "W132-120", "9": "W123-101", "10": "L116-103", "11": "L133-124 2OT", "12": "W115-107"}, "MIN": {"0": 12.0, "1": 25.0, "2": 12.0, "3": 11.0, "4": 10.0, "5": 13.0, "6": 6.0, "7": 34.0, "8": 12.0, "9": 12.0, "10": 21.0, "11": 9.0, "12": 9.0}, "FG": {"0": "1-2", "1": "2-4", "2": "1-2", "3": "2-6", "4": "2-6", "5": "1-1", "6": "1-1", "7": "8-11", "8": "3-3", "9": "0-0", "10": "4-5", "11": "0-0", "12": "2-3"}, "FG%": {"0": 50.0, "1": 50.0, "2": 50.0, "3": 33.3, "4": 33.3, "5": 100.0, "6": 100.0, "7": 72.7, "8": 100.0, "9": 0.0, "10": 80.0, "11": 0.0, "12": 66.7}, "3PT": {"0": "0-0", "1": "0-0", "2": "0-0", "3": "0-0", "4": "0-0", "5": "0-0", "6": "0-0", "7": "0-0", "8": "0-0", "9": "0-0", "10": "0-0", "11": "0-0", "12": "0-0"}, "3P%": {"0": 0.0, "1": 0.0, "2": 0.0, "3": 0.0, "4": 0.0, "5": 0.0, "6": 0.0, "7": 0.0, "8": 0.0, "9": 0.0, "10": 0.0, "11": 0.0, "12": 0.0}, "FT": {"0": "0-0", "1": "5-10", "2": "0-0", "3": "0-0", "4": "0-2", "5": "0-1", "6": "0-2", "7": "5-11", "8": "0-3", "9": "1-2", "10": "0-1", "11": "0-2", "12": "0-0"}, "FT%": {"0": 0.0, "1": 50.0, "2": 0.0, "3": 0.0, "4": 0.0, "5": 0.0, "6": 0.0, "7": 45.5, "8": 0.0, "9": 50.0, "10": 0.0, "11": 0.0, "12": 0.0}, "REB": {"0": 4.0, "1": 10.0, "2": 4.0, "3": 5.0, "4": 4.0, "5": 2.0, "6": 1.0, "7": 13.0, "8": 6.0, "9": 1.0, "10": 9.0, "11": 2.0, "12": 1.0}, "AST": {"0": 0.0, "1": 2.0, "2": 2.0, "3": 0.0, "4": 0.0, "5": 0.0, "6": 0.0, "7": 5.0, "8": 1.0, "9": 1.0, "10": 4.0, "11": 2.0, "12": 4.0}, "BLK": {"0": 1.0, "1": 2.0, "2": 0.0, "3": 1.0, "4": 0.0, "5": 0.0, "6": 0.0, "7": 1.0, "8": 0.0, "9": 0.0, "10": 0.0, "11": 0.0, "12": 0.0}, "STL": {"0": 0.0, "1": 1.0, "2": 1.0, "3": 0.0, "4": 0.0, "5": 0.0, "6": 0.0, "7": 2.0, "8": 0.0, "9": 0.0, "10": 2.0, "11": 0.0, "12": 1.0}, "PF": {"0": 2.0, "1": 5.0, "2": 2.0, "3": 0.0, "4": 0.0, "5": 2.0, "6": 0.0, "7": 3.0, "8": 3.0, "9": 2.0, "10": 3.0, "11": 1.0, "12": 1.0}, "TO": {"0": 1.0, "1": 2.0, "2": 1.0, "3": 0.0, "4": 1.0, "5": 2.0, "6": 0.0, "7": 2.0, "8": 1.0, "9": 1.0, "10": 5.0, "11": 0.0, "12": 1.0}, "PTS": {"0": 2.0, "1": 9.0, "2": 2.0, "3": 4.0, "4": 4.0, "5": 2.0, "6": 2.0, "7": 21.0, "8": 6.0, "9": 1.0, "10": 8.0, "11": 0.0, "12": 4.0}, "3PT_SA": {"0": 0.0, "1": 0.0, "2": 0.0, "3": 0.0, "4": 0.0, "5": 0.0, "6": 0.0, "7": 0.0, "8": 0.0, "9": 0.0, "10": 0.0, "11": 0.0, "12": 0.0}, "3PT_A": {"0": 0.0, "1": 0.0, "2": 0.0, "3": 0.0, "4": 0.0, "5": 0.0, "6": 0.0, "7": 0.0, "8": 0.0, "9": 0.0, "10": 0.0, "11": 0.0, "12": 0.0}}