{"Player": {"0": "jarred vanderbilt", "1": "jarred vanderbilt", "2": "jarred vanderbilt", "3": "jarred vanderbilt", "4": "jarred vanderbilt", "5": "jarred vanderbilt", "6": "jarred vanderbilt"}, "Season": {"0": "2023-24", "1": "2023-24", "2": "2023-24", "3": "2023-24", "4": "2023-24", "5": "2023-24", "6": "2023-24"}, "Type": {"0": "Regular", "1": "Regular", "2": "Tournament", "3": "Regular", "4": "Regular", "5": "Regular", "6": "Regular"}, "Date": {"0": "Fri 12/15", "1": "Wed 12/13", "2": "Sat 12/9", "3": "Thu 12/7", "4": "Tue 12/5", "5": "Sat 12/2", "6": "Sat 10/7"}, "OPP": {"0": "@SA", "1": "@SA", "2": "vsIND", "3": "vsNO", "4": "vsPHX", "5": "vsHOU", "6": "@GS"}, "Result": {"0": "L129-115", "1": "W122-119", "2": "W123-109", "3": "W133-89", "4": "W106-103", "5": "W107-97", "6": "L125-108"}, "MIN": {"0": 13.0, "1": 17.0, "2": 16.0, "3": 14.0, "4": 15.0, "5": 14.0, "6": 21.0}, "FG": {"0": "0-3", "1": "1-1", "2": "0-1", "3": "1-2", "4": "0-2", "5": "0-2", "6": "2-4"}, "FG%": {"0": 0.0, "1": 100.0, "2": 0.0, "3": 50.0, "4": 0.0, "5": 0.0, "6": 50.0}, "3PT": {"0": "0-1", "1": "0-0", "2": "0-0", "3": "0-0", "4": "0-2", "5": "0-2", "6": "2-3"}, "3P%": {"0": 0.0, "1": 0.0, "2": 0.0, "3": 0.0, "4": 0.0, "5": 0.0, "6": 66.7}, "FT": {"0": "0-0", "1": "0-0", "2": "0-0", "3": "0-0", "4": "1-2", "5": "0-0", "6": "0-2"}, "FT%": {"0": 0.0, "1": 0.0, "2": 0.0, "3": 0.0, "4": 50.0, "5": 0.0, "6": 0.0}, "REB": {"0": 5.0, "1": 3.0, "2": 4.0, "3": 5.0, "4": 6.0, "5": 4.0, "6": 7.0}, "AST": {"0": 1.0, "1": 0.0, "2": 1.0, "3": 1.0, "4": 2.0, "5": 1.0, "6": 1.0}, "BLK": {"0": 0.0, "1": 1.0, "2": 2.0, "3": 1.0, "4": 0.0, "5": 0.0, "6": 0.0}, "STL": {"0": 0.0, "1": 1.0, "2": 1.0, "3": 0.0, "4": 1.0, "5": 0.0, "6": 1.0}, "PF": {"0": 4.0, "1": 1.0, "2": 1.0, "3": 0.0, "4": 2.0, "5": 1.0, "6": 0.0}, "TO": {"0": 0.0, "1": 0.0, "2": 0.0, "3": 0.0, "4": 1.0, "5": 0.0, "6": 2.0}, "PTS": {"0": 0.0, "1": 2.0, "2": 0.0, "3": 2.0, "4": 1.0, "5": 0.0, "6": 6.0}, "3PT_SA": {"0": 0.0, "1": 0.0, "2": 0.0, "3": 0.0, "4": 0.0, "5": 0.0, "6": 2.0}, "3PT_A": {"0": 1.0, "1": 0.0, "2": 0.0, "3": 0.0, "4": 2.0, "5": 2.0, "6": 3.0}}