{"Player": {"0": "jayson tatum", "1": "jayson tatum", "2": "jayson tatum", "3": "jayson tatum", "4": "jayson tatum", "5": "jayson tatum", "6": "jayson tatum", "7": "jayson tatum", "8": "jayson tatum", "9": "jayson tatum", "10": "jayson tatum", "11": "jayson tatum", "12": "jayson tatum", "13": "jayson tatum", "14": "jayson tatum", "15": "jayson tatum", "16": "jayson tatum", "17": "jayson tatum", "18": "jayson tatum", "19": "jayson tatum", "20": "jayson tatum", "21": "jayson tatum", "22": "jayson tatum", "23": "jayson tatum", "24": "jayson tatum", "25": "jayson tatum", "26": "jayson tatum", "27": "jayson tatum", "28": "jayson tatum", "29": "jayson tatum", "30": "jayson tatum", "31": "jayson tatum", "32": "jayson tatum", "33": "jayson tatum", "34": "jayson tatum", "35": "jayson tatum", "36": "jayson tatum", "37": "jayson tatum"}, "Season": {"0": "2023-24", "1": "2023-24", "2": "2023-24", "3": "2023-24", "4": "2023-24", "5": "2023-24", "6": "2023-24", "7": "2023-24", "8": "2023-24", "9": "2023-24", "10": "2023-24", "11": "2023-24", "12": "2023-24", "13": "2023-24", "14": "2023-24", "15": "2023-24", "16": "2023-24", "17": "2023-24", "18": "2023-24", "19": "2023-24", "20": "2023-24", "21": "2023-24", "22": "2023-24", "23": "2023-24", "24": "2023-24", "25": "2023-24", "26": "2023-24", "27": "2023-24", "28": "2023-24", "29": "2023-24", "30": "2023-24", "31": "2023-24", "32": "2023-24", "33": "2023-24", "34": "2023-24", "35": "2023-24", "36": "2023-24", "37": "2023-24"}, "Type": {"0": "Regular", "1": "Regular", "2": "Regular", "3": "Regular", "4": "Regular", "5": "Regular", "6": "Regular", "7": "Regular", "8": "Regular", "9": "Regular", "10": "Regular", "11": "Regular", "12": "Regular", "13": "Regular", "14": "Regular", "15": "Regular", "16": "Regular", "17": "Regular", "18": "Regular", "19": "Regular", "20": "Regular", "21": "Regular", "22": "Regular", "23": "Regular", "24": "Regular", "25": "Regular", "26": "Regular", "27": "Regular", "28": "Regular", "29": "Regular", "30": "Regular", "31": "Regular", "32": "Regular", "33": "Regular", "34": "Regular", "35": "Preseason", "36": "Preseason", "37": "Preseason"}, "Date": {"0": "Thu 1/11", "1": "Wed 1/10", "2": "Sat 1/6", "3": "Fri 1/5", "4": "Tue 1/2", "5": "Sun 12/31", "6": "Thu 12/28", "7": "Mon 12/25", "8": "Sat 12/23", "9": "Tue 12/19", "10": "Sun 12/17", "11": "Fri 12/15", "12": "Thu 12/14", "13": "Tue 12/12", "14": "Fri 12/8", "15": "Mon 12/4", "16": "Fri 12/1", "17": "Tue 11/28", "18": "Sun 11/26", "19": "Fri 11/24", "20": "Wed 11/22", "21": "Mon 11/20", "22": "Sun 11/19", "23": "Fri 11/17", "24": "Wed 11/15", "25": "Mon 11/13", "26": "Sat 11/11", "27": "Fri 11/10", "28": "Wed 11/8", "29": "Mon 11/6", "30": "Sat 11/4", "31": "Wed 11/1", "32": "Mon 10/30", "33": "Fri 10/27", "34": "Wed 10/25", "35": "Thu 10/19", "36": "Tue 10/17", "37": "Sun 10/8"}, "OPP": {"0": "@MIL", "1": "vsMIN", "2": "@IND", "3": "vsUTAH", "4": "@OKC", "5": "@SA", "6": "vsDET", "7": "@LAL", "8": "@LAC", "9": "@GS", "10": "vsORL", "11": "vsORL", "12": "vsCLE", "13": "vsCLE", "14": "vsNY", "15": "@IND", "16": "vsPHI", "17": "vsCHI", "18": "vsATL", "19": "@ORL", "20": "vsMIL", "21": "@CHA", "22": "@MEM", "23": "@TOR", "24": "@PHI", "25": "vsNY", "26": "vsTOR", "27": "vsBKN", "28": "@PHI", "29": "@MIN", "30": "@BKN", "31": "vsIND", "32": "@WSH", "33": "vsMIA", "34": "@NY", "35": "@CHA", "36": "vsNY", "37": "vsPHI"}, "Result": {"0": "L135-102", "1": "W127-120 OT", "2": "W118-101", "3": "W126-97", "4": "L127-123", "5": "W134-101", "6": "W128-122 OT", "7": "W126-115", "8": "W145-108", "9": "L132-126 OT", "10": "W114-97", "11": "W128-111", "12": "W116-107", "13": "W120-113", "14": "W133-123", "15": "L122-112", "16": "W125-119", "17": "W124-97", "18": "W113-103", "19": "L113-96", "20": "W119-116", "21": "L121-118 OT", "22": "W102-100", "23": "W108-105", "24": "W117-107", "25": "W114-98", "26": "W117-94", "27": "W121-107", "28": "L106-103", "29": "L114-109 OT", "30": "W124-114", "31": "W155-104", "32": "W126-107", "33": "W119-111", "34": "W108-104", "35": "W127-99", "36": "W123-110", "37": "W114-106"}, "MIN": {"0": 16.0, "1": 42.0, "2": 38.0, "3": 25.0, "4": 38.0, "5": 31.0, "6": 43.0, "7": 41.0, "8": 30.0, "9": 41.0, "10": 31.0, "11": 39.0, "12": 36.0, "13": 41.0, "14": 39.0, "15": 37.0, "16": 27.0, "17": 36.0, "18": 39.0, "19": 39.0, "20": 36.0, "21": 44.0, "22": 35.0, "23": 37.0, "24": 39.0, "25": 39.0, "26": 34.0, "27": 33.0, "28": 37.0, "29": 43.0, "30": 41.0, "31": 27.0, "32": 28.0, "33": 41.0, "34": 39.0, "35": 23.0, "36": 30.0, "37": 27.0}, "FG": {"0": "2-6", "1": "13-26", "2": "14-23", "3": "6-12", "4": "10-21", "5": "10-17", "6": "11-31", "7": "6-15", "8": "9-16", "9": "5-17", "10": "8-21", "11": "11-22", "12": "9-22", "13": "7-19", "14": "8-18", "15": "13-26", "16": "6-9", "17": "8-16", "18": "11-25", "19": "7-16", "20": "7-17", "21": "15-28", "22": "7-13", "23": "8-22", "24": "10-23", "25": "13-23", "26": "10-18", "27": "6-17", "28": "6-14", "29": "12-22", "30": "10-20", "31": "9-15", "32": "14-21", "33": "9-22", "34": "13-22", "35": "4-12", "36": "9-15", "37": "3-13"}, "FG%": {"0": 33.3, "1": 50.0, "2": 60.9, "3": 50.0, "4": 47.6, "5": 58.8, "6": 35.5, "7": 40.0, "8": 56.3, "9": 29.4, "10": 38.1, "11": 50.0, "12": 40.9, "13": 36.8, "14": 44.4, "15": 50.0, "16": 66.7, "17": 50.0, "18": 44.0, "19": 43.8, "20": 41.2, "21": 53.6, "22": 53.8, "23": 36.4, "24": 43.5, "25": 56.5, "26": 55.6, "27": 35.3, "28": 42.9, "29": 54.5, "30": 50.0, "31": 60.0, "32": 66.7, "33": 40.9, "34": 59.1, "35": 33.3, "36": 60.0, "37": 23.1}, "3PT": {"0": "0-1", "1": "6-11", "2": "8-13", "3": "5-8", "4": "2-5", "5": "5-10", "6": "2-11", "7": "1-6", "8": "5-10", "9": "2-9", "10": "4-6", "11": "2-9", "12": "3-10", "13": "2-9", "14": "3-9", "15": "2-8", "16": "2-5", "17": "2-8", "18": "5-13", "19": "0-3", "20": "2-9", "21": "7-15", "22": "1-1", "23": "1-11", "24": "4-10", "25": "5-12", "26": "3-9", "27": "4-11", "28": "2-6", "29": "2-8", "30": "6-10", "31": "3-5", "32": "4-9", "33": "3-10", "34": "3-8", "35": "1-5", "36": "5-8", "37": "0-4"}, "3P%": {"0": 0.0, "1": 54.5, "2": 61.5, "3": 62.5, "4": 40.0, "5": 50.0, "6": 18.2, "7": 16.7, "8": 50.0, "9": 22.2, "10": 66.7, "11": 22.2, "12": 30.0, "13": 22.2, "14": 33.3, "15": 25.0, "16": 40.0, "17": 25.0, "18": 38.5, "19": 0.0, "20": 22.2, "21": 46.7, "22": 100.0, "23": 9.1, "24": 40.0, "25": 41.7, "26": 33.3, "27": 36.4, "28": 33.3, "29": 25.0, "30": 60.0, "31": 60.0, "32": 44.4, "33": 30.0, "34": 37.5, "35": 20.0, "36": 62.5, "37": 0.0}, "FT": {"0": "3-4", "1": "13-14", "2": "2-4", "3": "13-14", "4": "8-10", "5": "0-0", "6": "7-8", "7": "12-13", "8": "7-9", "9": "3-3", "10": "3-4", "11": "6-9", "12": "6-8", "13": "9-9", "14": "6-8", "15": "4-7", "16": "7-9", "17": "3-3", "18": "7-10", "19": "12-13", "20": "7-9", "21": "8-10", "22": "5-6", "23": "0-0", "24": "5-6", "25": "4-5", "26": "4-6", "27": "7-9", "28": "2-3", "29": "6-8", "30": "6-6", "31": "9-10", "32": "1-1", "33": "1-3", "34": "5-6", "35": "2-2", "36": "5-5", "37": "7-9"}, "FT%": {"0": 75.0, "1": 92.9, "2": 50.0, "3": 92.9, "4": 80.0, "5": 0.0, "6": 87.5, "7": 92.3, "8": 77.8, "9": 100.0, "10": 75.0, "11": 66.7, "12": 75.0, "13": 100.0, "14": 75.0, "15": 57.1, "16": 77.8, "17": 100.0, "18": 70.0, "19": 92.3, "20": 77.8, "21": 80.0, "22": 83.3, "23": 0.0, "24": 83.3, "25": 80.0, "26": 66.7, "27": 77.8, "28": 66.7, "29": 75.0, "30": 100.0, "31": 90.0, "32": 100.0, "33": 33.3, "34": 83.3, "35": 100.0, "36": 100.0, "37": 77.8}, "REB": {"0": 1.0, "1": 4.0, "2": 13.0, "3": 9.0, "4": 13.0, "5": 6.0, "6": 7.0, "7": 8.0, "8": 4.0, "9": 8.0, "10": 8.0, "11": 6.0, "12": 11.0, "13": 10.0, "14": 6.0, "15": 12.0, "16": 7.0, "17": 7.0, "18": 9.0, "19": 5.0, "20": 11.0, "21": 13.0, "22": 9.0, "23": 7.0, "24": 8.0, "25": 6.0, "26": 5.0, "27": 10.0, "28": 15.0, "29": 5.0, "30": 11.0, "31": 12.0, "32": 6.0, "33": 8.0, "34": 11.0, "35": 6.0, "36": 8.0, "37": 10.0}, "AST": {"0": 3.0, "1": 2.0, "2": 6.0, "3": 5.0, "4": 8.0, "5": 2.0, "6": 10.0, "7": 7.0, "8": 2.0, "9": 7.0, "10": 3.0, "11": 4.0, "12": 3.0, "13": 5.0, "14": 5.0, "15": 6.0, "16": 4.0, "17": 4.0, "18": 4.0, "19": 3.0, "20": 4.0, "21": 6.0, "22": 5.0, "23": 2.0, "24": 6.0, "25": 7.0, "26": 4.0, "27": 3.0, "28": 6.0, "29": 2.0, "30": 1.0, "31": 4.0, "32": 3.0, "33": 5.0, "34": 4.0, "35": 7.0, "36": 4.0, "37": 5.0}, "BLK": {"0": 0.0, "1": 0.0, "2": 0.0, "3": 1.0, "4": 0.0, "5": 2.0, "6": 0.0, "7": 1.0, "8": 0.0, "9": 0.0, "10": 1.0, "11": 0.0, "12": 3.0, "13": 2.0, "14": 0.0, "15": 0.0, "16": 1.0, "17": 0.0, "18": 0.0, "19": 0.0, "20": 1.0, "21": 2.0, "22": 1.0, "23": 0.0, "24": 0.0, "25": 0.0, "26": 1.0, "27": 0.0, "28": 0.0, "29": 0.0, "30": 0.0, "31": 0.0, "32": 0.0, "33": 0.0, "34": 1.0, "35": 0.0, "36": 1.0, "37": 0.0}, "STL": {"0": 0.0, "1": 1.0, "2": 1.0, "3": 1.0, "4": 1.0, "5": 0.0, "6": 5.0, "7": 0.0, "8": 1.0, "9": 2.0, "10": 0.0, "11": 0.0, "12": 0.0, "13": 0.0, "14": 1.0, "15": 1.0, "16": 1.0, "17": 0.0, "18": 2.0, "19": 2.0, "20": 0.0, "21": 0.0, "22": 1.0, "23": 1.0, "24": 2.0, "25": 1.0, "26": 0.0, "27": 0.0, "28": 3.0, "29": 5.0, "30": 0.0, "31": 0.0, "32": 0.0, "33": 1.0, "34": 2.0, "35": 3.0, "36": 3.0, "37": 1.0}, "PF": {"0": 2.0, "1": 3.0, "2": 4.0, "3": 1.0, "4": 3.0, "5": 1.0, "6": 4.0, "7": 0.0, "8": 0.0, "9": 0.0, "10": 3.0, "11": 3.0, "12": 1.0, "13": 3.0, "14": 3.0, "15": 2.0, "16": 1.0, "17": 2.0, "18": 2.0, "19": 3.0, "20": 2.0, "21": 1.0, "22": 4.0, "23": 3.0, "24": 1.0, "25": 5.0, "26": 2.0, "27": 1.0, "28": 2.0, "29": 2.0, "30": 1.0, "31": 1.0, "32": 2.0, "33": 4.0, "34": 3.0, "35": 1.0, "36": 3.0, "37": 2.0}, "TO": {"0": 1.0, "1": 1.0, "2": 4.0, "3": 1.0, "4": 4.0, "5": 3.0, "6": 3.0, "7": 1.0, "8": 2.0, "9": 0.0, "10": 1.0, "11": 2.0, "12": 3.0, "13": 4.0, "14": 0.0, "15": 2.0, "16": 7.0, "17": 4.0, "18": 6.0, "19": 2.0, "20": 2.0, "21": 3.0, "22": 8.0, "23": 3.0, "24": 3.0, "25": 3.0, "26": 1.0, "27": 2.0, "28": 2.0, "29": 6.0, "30": 3.0, "31": 2.0, "32": 2.0, "33": 2.0, "34": 4.0, "35": 2.0, "36": 2.0, "37": 1.0}, "PTS": {"0": 7.0, "1": 45.0, "2": 38.0, "3": 30.0, "4": 30.0, "5": 25.0, "6": 31.0, "7": 25.0, "8": 30.0, "9": 15.0, "10": 23.0, "11": 30.0, "12": 27.0, "13": 25.0, "14": 25.0, "15": 32.0, "16": 21.0, "17": 21.0, "18": 34.0, "19": 26.0, "20": 23.0, "21": 45.0, "22": 20.0, "23": 17.0, "24": 29.0, "25": 35.0, "26": 27.0, "27": 23.0, "28": 16.0, "29": 32.0, "30": 32.0, "31": 30.0, "32": 33.0, "33": 22.0, "34": 34.0, "35": 11.0, "36": 28.0, "37": 13.0}, "3PT_SA": {"0": 0.0, "1": 6.0, "2": 8.0, "3": 5.0, "4": 2.0, "5": 5.0, "6": 2.0, "7": 1.0, "8": 5.0, "9": 2.0, "10": 4.0, "11": 2.0, "12": 3.0, "13": 2.0, "14": 3.0, "15": 2.0, "16": 2.0, "17": 2.0, "18": 5.0, "19": 0.0, "20": 2.0, "21": 7.0, "22": 1.0, "23": 1.0, "24": 4.0, "25": 5.0, "26": 3.0, "27": 4.0, "28": 2.0, "29": 2.0, "30": 6.0, "31": 3.0, "32": 4.0, "33": 3.0, "34": 3.0, "35": 1.0, "36": 5.0, "37": 0.0}, "3PT_A": {"0": 1.0, "1": 11.0, "2": 13.0, "3": 8.0, "4": 5.0, "5": 10.0, "6": 11.0, "7": 6.0, "8": 10.0, "9": 9.0, "10": 6.0, "11": 9.0, "12": 10.0, "13": 9.0, "14": 9.0, "15": 8.0, "16": 5.0, "17": 8.0, "18": 13.0, "19": 3.0, "20": 9.0, "21": 15.0, "22": 1.0, "23": 11.0, "24": 10.0, "25": 12.0, "26": 9.0, "27": 11.0, "28": 6.0, "29": 8.0, "30": 10.0, "31": 5.0, "32": 9.0, "33": 10.0, "34": 8.0, "35": 5.0, "36": 8.0, "37": 4.0}}