{"mikal bridges": 31.48, "nic claxton": 27.37, "noah clowney": 4.7, "spencer dinwiddie": 23.53, "cameron johnson": 27.42, "keon johnson": 11.58, "royce o'neale": 23.75, "ben simmons": 20.06, "dennis smith jr": 19.87, "cam thomas": 31.91, "lonnie walker iv": 18.84, "trendon watford": 13.71, "nicolas batum": 24.14, "patrick beverley": 17.08, "tobias harris": 34.3, "danuel house jr": 15.04, "tyrese maxey": 37.67, "marcus morris sr": 15.5, "kelly oubre jr": 30.92, "paul reed": 22.32, "stephen curry": 31.87, "draymond green": 27.84, "trayce jackson davis": 11.35, "cory joseph": 10.07, "jonathan kuminga": 28.61, "kevon looney": 11.08, "brandin podziemski": 30.7, "klay thompson": 27.55, "andrew wiggins": 29.0, "bogdan bogdanovic": 33.2, "clint capela": 23.1, "jalen johnson": 35.37, "garrison mathews": 16.05, "patty mills": 0, "dejounte murray": 35.44, "onyeka okongwu": 33.0, "trae young": 35.0, "harrison barnes": 29.48, "chris duarte": 10.99, "keon ellis": 7.65, "de'aaron fox": 35.51, "kevin huerter": 25.55, "trey lyles": 19.56, "davion mitchell": 11.72, "malik monk": 25.73, "keegan murray": 32.55, "domantas sabonis": 36.07, "jevon carter": 13.7, "alex caruso": 29.84, "torrey craig": 23.33, "demar derozan": 38.78, "ayo dosunmu": 33.93, "andre drummond": 18.47, "nikola vucevic": 34.36, "coby white": 38.35, "max christie": 14.87, "anthony davis": 35.54, "rui hachimura": 29.29, "lebron james": 36.23, "taurean prince": 22.99, "austin reaves": 33.92, "d'angelo russell": 34.19, "christian wood": 11.67, "precious achiuwa": 35.15, "og anunoby": 34.88, "jalen brunson": 37.32, "donte divincenzo": 33.11, "evan fournier": 12.35, "josh hart": 39.32, "isaiah hartenstein": 24.78, "giannis antetokounmpo": 32.67, "malik beasley": 29.12, "marjon beauchamp": 8.67, "pat connaughton": 22.21, "jae crowder": 26.14, "andre jackson jr": 10.35, "damian lillard": 32.58, "brook lopez": 28.9, "khris middleton": 26.67, "cameron payne": 17.11, "bobby portis": 23.43, "seth curry": 19.89, "luka doncic": 36.6, "josh green": 28.37, "tim hardaway jr": 27.34, "jaden hardy": 9.1, "derrick jones jr": 16.8, "maxi kleber": 23.56, "dwight powell": 4.74, "grant williams": 26.05, "jarrett allen": 32.22, "darius garland": 35.21, "caris levert": 26.61, "sam merrill": 16.3, "donovan mitchell": 35.27, "evan mobley": 32.09, "georges niang": 20.01, "isaac okoro": 27.88, "craig porter": 13.71, "max strus": 33.52, "dean wade": 18.98, "dominick barlow": 12.18, "malaki branham": 22.32, "julian champagnie": 19.8, "zach collins": 21.91, "tre jones": 28.28, "doug mcdermott": 14.1, "cedi osman": 16.21, "jeremy sochan": 28.88, "devin vassell": 32.41, "victor wembanyama": 28.7, "blake wesley": 15.96, "saddiq bey": 31.91, "de'andre hunter": 27.34, "sasha vezenkov": 12.15, "keldon johnson": 26.54, "moses moody": 24.53, "cole anthony": 23.54, "paolo banchero": 34.03, "goga bitadze": 15.73, "anthony black": 19.35, "wendell carter jr": 25.48, "markelle fultz": 19.44, "gary harris": 23.36, "caleb houstan": 12.32, "joe ingles": 17.82, "jonathan isaac": 15.19, "chuma okeke": 3.0, "trevelin queen": 12.54, "jalen suggs": 24.58, "franz wagner": 32.37, "moritz wagner": 17.93, "bojan bogdanovic": 21.85, "alec burks": 15.86, "cade cunningham": 32.79, "jalen duren": 29.14, "danilo gallinari": 15.86, "killian hayes": 17.88, "jaden ivey": 29.63, "kevin knox ii": 0, "monte morris": 14.52, "marcus sasser": 21.65, "ausar thompson": 30.01, "james wiseman": 11.63, "grayson allen": 33.26, "keita bates diop": 0, "bradley beal": 33.59, "devin booker": 36.77, "kevin durant": 37.56, "drew eubanks": 15.78, "jordan goodwin": 18.24, "eric gordon": 31.4, "nassir little": 13.65, "theo maledon": 0, "chimezie metu": 0, "jusuf nurkic": 27.69, "josh okogie": 19.98, "yuta watanabe": 14.29, "deni avdija": 31.23, "bilal coulibaly": 27.02, "daniel gafford": 14.62, "tyus jones": 29.21, "corey kispert": 24.07, "jordan poole": 29.85, "landry shamet": 18.17, "delon wright": 15.51, "santi aldama": 27.64, "tosan evbuomwan": 15.73, "jacob gilyard": 18.33, "matt hurt": 13.86, "gg jackson": 22.22, "trey jemison": 21.56, "luke kennard": 26.63, "john konchar": 21.71, "scotty pippen jr": 23.2, "david roddy": 21.41, "derrick rose": 17.3, "vince williams jr": 31.17, "jaylen brown": 33.47, "sam hauser": 17.83, "jrue holiday": 32.73, "al horford": 23.8, "luke kornet": 10.68, "kristaps porzingis": 30.17, "payton pritchard": 18.39, "neemias queta": 12.22, "jayson tatum": 36.14, "derrick white": 31.88, "tyrese haliburton": 28.67, "buddy hield": 33.19, "isaiah jackson": 11.43, "bennedict mathurin": 22.72, "tj mcconnell": 18.32, "andrew nembhard": 29.6, "aaron nesmith": 29.49, "pascal siakam": 32.02, "jalen smith": 15.34, "myles turner": 26.75, "miles bridges": 37.34, "cody martin": 27.8, "bryce mcgowens": 16.28, "nathan mensah": 11.02, "brandon miller": 32.11, "nick richards": 27.19, "ish smith": 25.33, "nick smith jr": 16.38, "jt thor": 11.28, "pj washington": 30.91, "amir coffey": 16.58, "paul george": 34.2, "james harden": 33.52, "bones hyland": 7.06, "kawhi leonard": 34.1, "terance mann": 25.62, "mason plumlee": 11.68, "norman powell": 25.12, "daniel theis": 16.61, "pj tucker": 13.44, "russell westbrook": 21.13, "bam adebayo": 34.03, "jimmy butler": 33.55, "jamal cain": 15.53, "tyler herro": 34.23, "haywood highsmith": 20.27, "jaime jaquez jr": 28.9, "nikola jovic": 17.97, "kevin love": 16.79, "caleb martin": 26.24, "josh richardson": 26.32, "orlando robinson": 13.52, "terry rozier": 32.86, "dillon brooks": 31.03, "jalen green": 30.02, "jeff green": 14.86, "aaron holiday": 15.64, "alperen sengun": 31.9, "jabari smith jr": 31.16, "jae'sean tate": 16.21, "amen thompson": 17.9, "fred vanvleet": 36.62, "cam whitmore": 17.25, "nickeil alexander walker": 20.91, "kyle anderson": 20.78, "mike conley": 28.0, "anthony edwards": 34.85, "rudy gobert": 33.49, "jaden mcdaniels": 28.57, "shake milton": 13.63, "naz reid": 22.78, "karl anthony towns": 31.82, "scottie barnes": 36.07, "rj barrett": 32.83, "chris boucher": 12.65, "bruce brown": 24.23, "gradey dick": 17.62, "jordan nwora": 13.55, "jakob poeltl": 26.22, "otto porter jr": 9.67, "immanuel quickley": 34.01, "dennis schroder": 30.04, "gary trent jr": 29.64, "thaddeus young": 12.0, "ousmane dieng": 11.62, "luguentz dort": 28.33, "josh giddey": 23.73, "shai gilgeous alexander": 34.42, "chet holmgren": 30.27, "vasilije micic": 16.82, "cason wallace": 19.5, "aaron wiggins": 14.46, "jaylin williams": 13.11, "kenrich williams": 13.67, "ochai agbaji": 16.48, "jordan clarkson": 30.01, "john collins": 29.8, "kris dunn": 17.49, "simone fontecchio": 19.1, "keyonte george": 30.57, "taylor hendricks": 21.71, "talen horton tucker": 19.38, "walker kessler": 23.02, "lauri markkanen": 33.55, "kelly olynyk": 20.91, "collin sexton": 25.56, "deandre ayton": 30.98, "ibou badji": 10.79, "malcolm brogdon": 34.67, "toumani camara": 24.93, "jerami grant": 33.78, "scoot henderson": 32.67, "kris murray": 16.31, "duop reath": 16.85, "shaedon sharpe": 27.67, "anfernee simons": 33.31, "matisse thybulle": 23.23, "jabari walker": 23.38, "christian braun": 17.99, "kentavious caldwell pope": 31.1, "aaron gordon": 30.74, "justin holiday": 9.53, "reggie jackson": 20.45, "nikola jokic": 34.27, "deandre jordan": 7.0, "jamal murray": 31.57, "michael porter jr": 31.1, "julian strawther": 10.54, "peyton watson": 18.24, "kyle lowry": 27.92, "ivica zubac": 26.64, "obi toppin": 16.17, "dario saric": 14.04, "jose alvarado": 17.58, "dyson daniels": 23.33, "jordan hawkins": 16.72, "brandon ingram": 33.2, "herbert jones": 28.97, "naji marshall": 19.33, "cj mccollum": 31.41, "trey murphy iii": 27.83, "larry nance jr": 19.01, "matt ryan": 15.54, "jonas valanciunas": 23.97, "zion williamson": 30.41, "kyrie irving": 34.8, "dariq whitehead": 12.0, "duncan robinson": 27.39, "jalen williams": 32.08, "xavier tillman": 0, "jontay porter": 12.72, "gordon hayward": 14.62, "marvin bagley iii": 27.67, "kyle kuzma": 32.73, "mike muscala": 12.78, "quentin grimes": 15.81, "jaren jackson jr": 32.12, "jaden springer": 17.53, "isaiah joe": 18.63, "dorian finney smith": 25.35, "de'anthony melton": 22.66, "tari eason": 25.33, "gary payton ii": 13.9, "miles mcbride": 17.29, "lester quinones": 4.64, "davis bertans": 11.25, "tre mann": 25.29, "dalano banton": 10.34, "ashton hagans": 15.98, "day'ron sharpe": 15.96, "jalen wilson": 20.21, "troy brown jr": 10.05, "stanley umude": 18.41, "ziaire williams": 23.74, "dereck lively ii": 20.45, "cam reddish": 17.59, "lamelo ball": 30.0, "mark williams": 27.0, "chris paul": 24.59, "robert williams iii": 16.67, "jarred vanderbilt": 16.33, "gabe vincent": 23.67, "patrick williams": 29.94, "zach lavine": 31.67, "jake laravia": 16.58, "lamar stevens": 16.26, "isaiah stewart": 30.45, "dante exum": 13.47, "jericho sims": 17.84, "ben sheppard": 8.86, "isaiah livers": 19.0}